{"id": 631, "nome": "heatmor", "height": 14, "weight": 580, "is_default": "Verdadeiro", "moves": ["fire-punch", "thunder-punch", "cut", "bind", "tackle", "body-slam", "wrap", "flamethrower", "low-kick", "solar-beam", "fire-spin", "dig", "toxic", "double-team", "lick", "fire-blast", "amnesia", "fury-swipes", "rest", "slash", "substitute", "thief", "snore", "curse", "protect", "feint-attack", "giga-drain", "endure", "swagger", "attract", "sleep-talk", "return", "frustration", "pursuit", "hidden-power", "rain-dance", "sunny-day", "rock-smash", "stockpile", "spit-up", "swallow", "heat-wave", "will-o-wisp", "facade", "focus-punch", "taunt", "superpower", "recycle", "knock-off", "snatch", "secret-power", "overheat", "odor-sleuth", "rock-tomb", "tickle", "aerial-ace", "fling", "gastro-acid", "sucker-punch", "flare-blitz", "night-slash", "drain-punch", "focus-blast", "giga-impact", "shadow-claw", "bug-bite", "hone-claws", "flame-burst", "round", "incinerate", "inferno", "belch", "confide", "power-up-punch", "throat-chop", "fire-lash", "brutal-swing", "stomping-tantrum", "burning-jealousy", "scorching-sands"]}