{"id": 10233, "nome": "typhlosion-hisui", "height": 16, "weight": 698, "is_default": "Falso", "moves": ["fire-punch", "thunder-punch", "tackle", "body-slam", "take-down", "double-edge", "leer", "roar", "ember", "flamethrower", "hyper-beam", "low-kick", "solar-beam", "fire-spin", "earthquake", "dig", "quick-attack", "night-shade", "smokescreen", "confuse-ray", "defense-curl", "fire-blast", "swift", "rest", "rock-slide", "substitute", "flame-wheel", "curse", "reversal", "spite", "protect", "endure", "rollout", "sleep-talk", "sunny-day", "shadow-ball", "heat-wave", "will-o-wisp", "facade", "focus-punch", "brick-break", "endeavor", "eruption", "blast-burn", "overheat", "aerial-ace", "calm-mind", "gyro-ball", "flare-blitz", "focus-blast", "giga-impact", "shadow-claw", "fire-fang", "zen-headbutt", "lava-plume", "iron-head", "flame-charge", "hex", "inferno", "fire-pledge", "bulldoze", "wild-charge", "play-rough", "stomping-tantrum", "burning-jealousy", "poltergeist", "infernal-parade", "tera-blast", "temper-flare"]}